README.rst
setup.py
rounding/__init__.py
rounding/common.py
rounding/standard.py
rounding/stochastic.py
rounding.egg-info/PKG-INFO
rounding.egg-info/SOURCES.txt
rounding.egg-info/dependency_links.txt
rounding.egg-info/requires.txt
rounding.egg-info/top_level.txt