Metadata-Version: 1.1
Name: rounding
Version: 0.03
Summary: Stochastic Rounding
Home-page: http://dmaust.github.io/rounding/
Author: David Maust
Author-email: david@dmaust.net
License: Apache License, Version 2.0
Platform: UNKNOWN
Classifier: Development Status :: 3 - Alpha
Classifier: Intended Audience :: Science/Research
Classifier: License :: OSI Approved :: Apache Software License
